no---pysodium/__init__.py
simple_asym/__init__.py
simple_asym/asymmetric_encryption.py
simple_asym/crypto.py
simple_asym/exceptions.py
simple_asym/test.py
simple_asymmetric-0.6.1.dist-info/DESCRIPTION.rst
simple_asymmetric-0.6.1.dist-info/METADATA
simple_asymmetric-0.6.1.dist-info/RECORD
simple_asymmetric-0.6.1.dist-info/WHEEL
simple_asymmetric-0.6.1.dist-info/metadata.json
simple_asymmetric-0.6.1.dist-info/top_level.txt
