Metadata-Version: 2.0
Name: simple-asymmetric
Version: 0.6.1
Summary: An easy way to do combined AES and RSA encryption with python
Home-page: https://github.com/burke-software/simple-asymmetric-python
Author: David Burke
Author-email: david@burkesoftware.com
License: Apache License 2.0
Keywords: encryption
Platform: UNKNOWN
Classifier: Development Status :: 5 - Production/Stable
Classifier: Programming Language :: Python
Classifier: Programming Language :: Python :: 3
Classifier: Intended Audience :: Developers
Requires-Dist: pysodium (>=0.7.0-0)
